umodules/__init__.py
umodules/__main__.py
umodules/command.py
umodules/config.py
umodules/helper.py
umodules/module.py
umodules/module_type.py
umodules/parser.py
umodules/project.py
umodules/test.py
umodules/umodules.py
umodules/commands/clean.plugin
umodules/commands/clean.py
umodules/commands/edit.plugin
umodules/commands/edit.py
umodules/commands/install.plugin
umodules/commands/install.py
umodules/commands/new.plugin
umodules/commands/new.py
umodules/commands/status.plugin
umodules/commands/status.py
umodules/commands/update.plugin
umodules/commands/update.py
umodules/lib/__init__.py
umodules/lib/command.py
umodules/lib/config.py
umodules/lib/module.py
umodules/lib/parser.py
umodules/lib/project.py
umodules/lib/unity.py
umodules/lib/commands/__init__.py
umodules/lib/commands/command.py
umodules/lib/commands/install.plugin
umodules/lib/commands/install.py
umodules/lib/modules/__init__.py
umodules/lib/modules/git.plugin
umodules/lib/modules/git.py
umodules/lib/modules/module.py
umodules/lib/modules/template.plugin
umodules/lib/modules/template.py
umodules/lib/modules/test.plugin
umodules/lib/modules/test.py
umodules/module_types/git.plugin
umodules/module_types/git.py
umodules/module_types/local_copy.plugin
umodules/module_types/local_copy.py
umodules/module_types/local_unity_package.plugin
umodules/module_types/local_unity_package.py
umodules/module_types/remote_unity_package.plugin
umodules/module_types/remote_unity_package.py
umodules/module_types/template.plugin
umodules/module_types/template.py
umodules/module_types/test.plugin
umodules/module_types/test.py
umodules/modules/git.plugin
umodules/modules/git.py
umodules/modules/template.plugin
umodules/modules/template.py
umodules/modules/test.plugin
umodules/modules/test.py
umodules-0.7.1.dist-info/DESCRIPTION.rst
umodules-0.7.1.dist-info/METADATA
umodules-0.7.1.dist-info/RECORD
umodules-0.7.1.dist-info/WHEEL
umodules-0.7.1.dist-info/entry_points.txt
umodules-0.7.1.dist-info/metadata.json
umodules-0.7.1.dist-info/top_level.txt
umodules-0.7.1.dist-info/zip-safe
