Metadata-Version: 2.0
Name: umodules
Version: 0.7.1
Summary: Organize your Unity Projects with uModules
Home-page: https://gitlab.com/umodules/umodules
Author: sP0CkEr2
Author-email: paul@spocker.net
License: MIT
Platform: UNKNOWN
Classifier: Development Status :: 4 - Beta
Classifier: License :: OSI Approved :: MIT License
Classifier: Natural Language :: English
Classifier: Operating System :: MacOS
Classifier: Operating System :: Microsoft :: Windows
Classifier: Programming Language :: Python :: 3.4
Classifier: Programming Language :: Python :: 3.5
Classifier: Programming Language :: Python :: 3.6
Classifier: Topic :: Utilities
Classifier: Topic :: Games/Entertainment
Requires-Dist: dotmap
Requires-Dist: gitpython
Requires-Dist: markdown
Requires-Dist: munch
Requires-Dist: progress
Requires-Dist: pyyaml
Requires-Dist: wget
Requires-Dist: yapsy
